ydotool/__init__.py
ydotool/daemon.py
ydotool/ydotool.py
pyydotool-1.0.0.dist-info/WHEEL
pyydotool-1.0.0.dist-info/METADATA
pyydotool-1.0.0.dist-info/RECORD
