Metadata-Version: 2.1
Name: pyydotool
Version: 1.0.0
Summary: Python bindings to ydotool
Home-page: https://gitlab.com/jdsieci/pyydotool
License: LGPL-3.0-or-later
Author: Jerzy Drozdz
Author-email: jerzy.drozdz@jdsieci.pl
Requires-Python: >=3.10,<4.0
Classifier: License :: OSI Approved :: GNU Lesser General Public License v3 or later (LGPLv3+)
Classifier: Programming Language :: Python :: 3
Project-URL: Repository, https://gitlab.com/jdsieci/pyydotool
